[
  // ========================================== 
  //               Sidebar 
  // ==========================================
  {
    "key": "ctrl+j",
    "command": "workbench.action.toggleSidebarVisibility"
  },
  {
    "key": "ctrl+g",
    "command": "workbench.view.scm",
    "when": "workbench.scm.active"
  },
  // ------------- File Manager -----------------
  // j - move down; k - move up
  {
    "key": "ctrl+e",
    "command": "workbench.files.action.focusFilesExplorer"
  },
  {
    "key": "o",
    "command": "explorer.newFile",
    "when": "explorerViewletVisible && filesExplorerFocus && !inputFocus"
  },
  {
    "key": "i",
    "command": "renameFile",
    "when": "explorerViewletVisible && filesExplorerFocus && !inputFocus"
  },
  {
    "key": "d",
    "command": "moveFileToTrash",
    "when": "explorerResourceMoveableToTrash && filesExplorerFocus && foldersViewVisible && !explorerResourceReadonly && !inputFocus"
  },
  {
    "key": "r",
    "command": "renameFile",
    "when": "filesExplorerFocus && foldersViewVisible && !explorerResourceIsRoot && !explorerResourceReadonly && !inputFocus"
  }
]
